ai_workspace/__init__.py
ai_workspace/hello.py
ai_workspace-0.1.1.dist-info/METADATA
ai_workspace-0.1.1.dist-info/WHEEL
ai_workspace-0.1.1.dist-info/top_level.txt
ai_workspace-0.1.1.dist-info/RECORD
